katmer/__init__.py
katmer/__main__.py
katmer/initializers.py
katmer/light.py
katmer/metrics.py
katmer/nk_post_processors.py
katmer/objective.py
katmer/optimize.py
katmer/plots.py
katmer/spec2materialdist.py
katmer/stack.py
katmer/tmm.py
katmer/utils.py
katmer-1.0.0.dist-info/LICENSE
katmer-1.0.0.dist-info/METADATA
katmer-1.0.0.dist-info/WHEEL
katmer-1.0.0.dist-info/entry_points.txt
katmer-1.0.0.dist-info/top_level.txt
katmer-1.0.0.dist-info/RECORD
