Metadata-Version: 2.1
Name: katmer
Version: 1.0.0
Summary: project_description
Home-page: https://github.com/bahremsd/katmer/
Author: bahremsd
License-File: LICENSE
Requires-Dist: jax >=0.5.0
Requires-Dist: equinox >=0.11.11
Requires-Dist: optax >=0.2.4
Requires-Dist: matplotlib >=3.10.0
Requires-Dist: numpy >=2.2.2
Requires-Dist: pandas >=2.2.3
Requires-Dist: scipy >=1.15.1
Requires-Dist: tmmax >=1.1.2
